Workbook

Sheet Dashboard
A1: INVENTORY & SUPPLY CHAIN ANALYSIS
A3: TOTAL INVENTORY VALUE | B3: TOTAL STOCK QUANTITY | C3: TOTAL REVENUE | D3: STOCKOUT RECORDS | E3: LOST SALES UNITS | F3: AVERAGE LEAD TIME (DAYS) | H3: Stockout Status | I3: Number of Records
A4: =SUM(items_and_stock!O2:O3601) -> 38110323 | B4: =SUM(items_and_stock!N2:N3601) -> 1832833 | C4: =SUM(items_and_stock!U2:U3601) -> 23766768 | D4: =COUNTIF(items_and_stock!W2:W3601,"Y") -> 114 | E4: =SUM(items_and_stock!V2:V3601) -> 15934 | F4: =AVERAGE(items_and_stock!L2:L3601) -> 37.138155 | H4: Y | I4: =COUNTIF(items_and_stock!$W:$W,"Y") -> 114
H5: N | I5: =COUNTIF(items_and_stock!$W:$W,"N") -> 3486

Sheet items_and_stock
A1: Item code | B1: Description | C1: Category | D1: Supplier | E1: Warehouse | F1: Period | G1: Unit cost | H1: Landed cost (with freight) | I1: Average cost (stock value / qty) | J1: Selling price | K1: Lead time planned days | L1: Lead time actual days | M1: Qty received | N1: Qty on hand | O1: Stock value | P1: Qty allocated to orders | Q1: Qty available | R1: Weeks of cover | S1: Days since last sale (month end) | T1: Units sold | U1: Revenue | V1: Lost sales units (stockout) | W1: Stocked out (Y/N) | X1: Availability Check
A2: IT-10001 | B2: Ball bearing 20-1 | C2: Bearings | D2: Clearwater Supply | E2: Main warehouse | F2: 2024-09 | G2: 1.1 | H2: 1.1 | I2: 1.084438 | J2: 1.45 | K2: 25 | L2: 24 | M2: 168 | N2: 489 | O2: 530.29 | P2: 13 | Q2: 476 | R2: 14.09 | S2: 2 | T2: 204 | U2: 295.8 | V2: 0 | W2: N | X2: =IF(Table2[[#This Row],[Qty available]]>Table2[[#This Row],[Qty on hand]],"Check","OK") -> OK
A3: IT-10001 | B3: Ball bearing 20-1 | C3: Bearings | D3: Clearwater Supply | E3: Main warehouse | F3: 2024-10 | G3: 1.07 | H3: 1.07 | I3: 1.082943 | J3: 1.45 | K3: 25 | L3: 24 | M3: 56 | N3: 384 | O3: 415.85 | P3: 57 | Q3: 327 | R3: 9.72 | S3: 1 | T3: 161 | U3: 233.45 | V3: 0 | W3: N | X3: =IF(Table2[[#This Row],[Qty available]]>Table2[[#This Row],[Qty on hand]],"Check","OK") -> OK
A4: IT-10001 | B4: Ball bearing 20-1 | C4: Bearings | D4: Clearwater Supply | E4: Main warehouse | F4: 2024-11 | G4: 1.07 | H4: 1.07 | I4: 1.076872 | J4: 1.45 | K4: 25 | L4: 23 | M4: 340 | N4: 438 | O4: 471.67 | P4: 51 | Q4: 387 | R4: 8.75 | S4: 1 | T4: 286 | U4: 414.7 | V4: 0 | W4: N | X4: =IF(Table2[[#This Row],[Qty available]]>Table2[[#This Row],[Qty on hand]],"Check","OK") -> OK
A5: IT-10001 | B5: Ball bearing 20-1 | C5: Bearings | D5: Clearwater Supply | E5: Main warehouse | F5: 2024-12 | G5: 1.09 | H5: 1.09 | I5: 1.082397 | J5: 1.45 | K5: 25 | L5: 23 | M5: 318 | N5: 655 | O5: 708.97 | P5: 57 | Q5: 598 | R5: 15.71 | S5: 0 | T5: 101 | U5: 146.45 | V5: 0 | W5: N | X5: =IF(Table2[[#This Row],[Qty available]]>Table2[[#This Row],[Qty on hand]],"Check","OK") -> OK
A6: IT-10001 | B6: Ball bearing 20-1 | C6: Bearings | D6: Clearwater Supply | E6: Main warehouse | F6: 2025-01 | G6: 1.07 | H6: 1.07 | I6: 1.081253 | J6: 1.45 | K6: 25 | L6: 23 | M6: 67 | N6: 471 | O6: 509.27 | P6: 13 | Q6: 458 | R6: 9.7 | S6: 0 | T6: 251 | U6: 363.95 | V6: 0 | W6: N | X6: =IF(Table2[[#This Row],[Qty available]]>Table2[[#This Row],[Qty on hand]],"Check","OK") -> OK
A7: IT-10001 | B7: Ball bearing 20-1 | C7: Bearings | D7: Clearwater Supply | E7: Main warehouse | F7: 2025-02 | G7: 1.09 | H7: 1.09 | I7: 1.081596 | J7: 1.49 | K7: 25 | L7: 22 | M7: 19 | N7: 307 | O7: 332.05 | P7: 64 | Q7: 243 | R7: 7.38 | S7: 0 | T7: 183 | U7: 272.67 | V7: 0 | W7: N | X7: =IF(Table2[[#This Row],[Qty available]]>Table2[[#This Row],[Qty on hand]],"Check","OK") -> OK
A8: IT-10001 | B8: Ball bearing 20-1 | C8: Bearings | D8: Clearwater Supply | E8: Main warehouse | F8: 2025-03 | G8: 1.09 | H8: 1.09 | I8: 1.087405 | J8: 1.49 | K8: 25 | L8: 25 | M8: 689 | N8: 790 | O8: 859.05 | P8: 25 | Q8: 765 | R8: 15.87 | S8: 3 | T8: 206 | U8: 306.94 | V8: 0 | W8: N | X8: =IF(Table2[[#This Row],[Qty available]]>Table2[[#This Row],[Qty on hand]],"Check","OK") -> OK
A9: IT-10001 | B9: Ball bearing 20-1 | C9: Bearings | D9: Clearwater Supply | E9: Main warehouse | F9: 2025-04 | G9: 1.12 | H9: 1.12 | I9: 1.091548 | J9: 1.49 | K9: 25 | L9: 25 | M9: 115 | N9: 691 | O9: 754.26 | P9: 19 | Q9: 672 | R9: 14.57 | S9: 3 | T9: 214 | U9: 318.86 | V9: 0 | W9: N | X9: =IF(Table2[[#This Row],[Qty available]]>Table2[[#This Row],[Qty on hand]],"Check","OK") -> OK
A10: IT-10001 | B10: Ball bearing 20-1 | C10: Bearings | D10: Clearwater Supply | E10: Main warehouse | F10: 2025-05 | G10: 1.11 | H10: 1.11 | I10: 1.092201 | J10: 1.49 | K10: 25 | L10: 22 | M10: 25 | N10: 427 | O10: 466.37 | P10: 44 | Q10: 383 | R10: 7.92 | S10: 0 | T10: 289 | U10: 430.61 | V10: 0 | W10: N | X10: =IF(Table2[[#This Row],[Qty available]]>Table2[[#This Row],[Qty on hand]],"Check","OK") -> OK
A11: IT-10001 | B11: Ball bearing 20-1 | C11: Bearings | D11: Clearwater Supply | E11: Main warehouse | F11: 2025-06 | G11: 1.12 | H11: 1.12 | I11: 1.096409 | J11: 1.49 | K11: 25 | L11: 23 | M11: 76 | N11: 337 | O11: 369.49 | P11: 19 | Q11: 318 | R11: 6.55 | S11: 1 | T11: 166 | U11: 247.34 | V11: 0 | W11: N | X11: =IF(Table2[[#This Row],[Qty available]]>Table2[[#This Row],[Qty on hand]],"Check","OK") -> OK
A12: IT-10001 | B12: Ball bearing 20-1 | C12: Bearings | D12: Clearwater Supply | E12: Main warehouse | F12: 2025-07 | G12: 1.09 | H12: 1.09 | I12: 1.093865 | J12: 1.49 | K12: 25 | L12: 23 | M12: 220 | N12: 326 | O12: 356.6 | P12: 19 | Q12: 307 | R12: 6.25 | S12: 0 | T12: 231 | U12: 344.19 | V12: 0 | W12: N | X12: =IF(Table2[[#This Row],[Qty available]]>Table2[[#This Row],[Qty on hand]],"Check","OK") -> OK
A13: IT-10001 | B13: Ball bearing 20-1 | C13: Bearings | D13: Clearwater Supply | E13: Main warehouse | F13: 2025-08 | G13: 1.09 | H13: 1.09 | I13: 1.09381 | J13: 1.49 | K13: 25 | M13: 0 | N13: 42 | O13: 45.94 | P13: 42 | Q13: 0 | R13: 0.81 | S13: 0 | T13: 284 | U13: 423.16 | V13: 0 | W13: N | X13: =IF(Table2[[#This Row],[Qty available]]>Table2[[#This Row],[Qty on hand]],"Check","OK") -> OK
A14: IT-10001 | B14: Ball bearing 20-1 | C14: Bearings | D14: Clearwater Supply | E14: Main warehouse | F14: 2025-09 | G14: 1.12 | H14: 1.12 | I14: 1.117529 | J14: 1.49 | K14: 25 | L14: 38 | M14: 406 | N14: 259 | O14: 289.44 | P14: 13 | Q14: 246 | R14: 4.84 | S14: 0 | T14: 189 | U14: 281.61 | V14: 0 | W14: N | X14: =IF(Table2[[#This Row],[Qty available]]>Table2[[#This Row],[Qty on hand]],"Check","OK") -> OK
A15: IT-10001 | B15: Ball bearing 20-1 | C15: Bearings | D15: Clearwater Supply | E15: Main warehouse | F15: 2025-10 | G15: 1.11 | H15: 1.11 | I15: 1.113628 | J15: 1.49 | K15: 25 | L15: 36 | M15: 280 | N15: 452 | O15: 503.36 | P15: 25 | Q15: 427 | R15: 10.61 | S15: 7 | T15: 87 | U15: 129.63 | V15: 0 | W15: N | X15: =IF(Table2[[#This Row],[Qty available]]>Table2[[#This Row],[Qty on hand]],"Check","OK") -> OK
A16: IT-10001 | B16: Ball bearing 20-1 | C16: Bearings | D16: Clearwater Supply | E16: Main warehouse | F16: 2025-11 | G16: 1.1 | H16: 1.1 | I16: 1.109823 | J16: 1.49 | K16: 25 | L16: 39 | M16: 175 | N16: 453 | O16: 502.75 | P16: 32 | Q16: 421 | R16: 13.09 | S16: 8 | T16: 174 | U16: 259.26 | V16: 0 | W16: N | X16: =IF(Table2[[#This Row],[Qty available]]>Table2[[#This Row],[Qty on hand]],"Check","OK") -> OK
A17: IT-10001 | B17: Ball bearing 20-1 | C17: Bearings | D17: Clearwater Supply | E17: Main warehouse | F17: 2025-12 | G17: 1.09 | H17: 1.09 | I17: 1.102412 | J17: 1.49 | K17: 25 | L17: 22 | M17: 270 | N17: 456 | O17: 502.7 | P17: 38 | Q17: 418 | R17: 11.35 | S17: 2 | T17: 267 | U17: 397.83 | V17: 0 | W17: N | X17: =IF(Table2[[#This Row],[Qty available]]>Table2[[#This Row],[Qty on hand]],"Check","OK") -> OK
A18: IT-10001 | B18: Ball bearing 20-1 | C18: Bearings | D18: Clearwater Supply | E18: Main warehouse | F18: 2026-01 | G18: 1.11 | H18: 1.11 | I18: 1.105992 | J18: 1.49 | K18: 25 | L18: 25 | M18: 406 | N18: 781 | O18: 863.78 | P18: 64 | Q18: 717 | R18: 19.66 | S18: 2 | T18: 81 | U18: 120.69 | V18: 0 | W18: N | X18: =IF(Table2[[#This Row],[Qty available]]>Table2[[#This Row],[Qty on hand]],"Check","OK") -> OK
A19: IT-10001 | B19: Ball bearing 20-1 | C19: Bearings | D19: Clearwater Supply | E19: Main warehouse | F19: 2026-02 | G19: 1.1 | H19: 1.1 | I19: 1.106 | J19: 1.53 | K19: 25 | M19: 0 | N19: 605 | O19: 669.13 | P19: 44 | Q19: 561 | R19: 14.84 | S19: 1 | T19: 176 | U19: 269.28 | V19: 0 | W19: N | X19: =IF(Table2[[#This Row],[Qty available]]>Table2[[#This Row],[Qty on hand]],"Check","OK") -> OK
A20: IT-10001 | B20: Ball bearing 20-1 | C20: Bearings | D20: Clearwater Supply | E20: Main warehouse | F20: 2026-03 | G20: 1.1 | H20: 1.1 | I20: 1.104441 | J20: 1.53 | K20: 25 | L20: 23 | M20: 211 | N20: 572 | O20: 631.74 | P20: 32 | Q20: 540 | R20: 14.68 | S20: 1 | T20: 244 | U20: 373.32 | V20: 0 | W20: N | X20: =IF(Table2[[#This Row],[Qty available]]>Table2[[#This Row],[Qty on hand]],"Check","OK") -> OK
A21: IT-10001 | B21: Ball bearing 20-1 | C21: Bearings | D21: Clearwater Supply | E21: Main warehouse | F21: 2026-04 | G21: 1.14 | H21: 1.14 | I21: 1.107657 | J21: 1.53 | K21: 25 | L21: 24 | M21: 57 | N21: 606 | O21: 671.24 | P21: 57 | Q21: 549 | R21: 17.39 | S21: 15 | T21: 23 | U21: 35.19 | V21: 0 | W21: N | X21: =IF(Table2[[#This Row],[Qty available]]>Table2[[#This Row],[Qty on hand]],"Check","OK") -> OK
A22: IT-10001 | B22: Ball bearing 20-1 | C22: Bearings | D22: Clearwater Supply | E22: Main warehouse | F22: 2026-05 | G22: 1.15 | H22: 1.15 | I22: 1.111412 | J22: 1.53 | K22: 25 | L22: 22 | M22: 59 | N22: 432 | O22: 480.13 | P22: 51 | Q22: 381 | R22: 11.36 | S22: 3 | T22: 233 | U22: 356.49 | V22: 0 | W22: N | X22: =IF(Table2[[#This Row],[Qty available]]>Table2[[#This Row],[Qty on hand]],"Check","OK") -> OK
A23: IT-10001 | B23: Ball bearing 20-1 | C23: Bearings | D23: Clearwater Supply | E23: Main warehouse | F23: 2026-06 | G23: 1.15 | H23: 1.15 | I23: 1.124268 | J23: 1.53 | K23: 25 | L23: 25 | M23: 216 | N23: 478 | O23: 537.4 | P23: 25 | Q23: 453 | R23: 14.59 | S23: 2 | T23: 170 | U23: 260.1 | V23: 0 | W23: N | X23: =IF(Table2[[#This Row],[Qty available]]>Table2[[#This Row],[Qty on hand]],"Check","OK") -> OK
A24: IT-10001 | B24: Ball bearing 20-1 | C24: Bearings | D24: Clearwater Supply | E24: Main warehouse | F24: 2026-07 | G24: 1.13 | H24: 1.13 | I24: 1.124258 | J24: 1.53 | K24: 25 | M24: 0 | N24: 364 | O24: 409.23 | P24: 64 | Q24: 300 | R24: 9.25 | S24: 3 | T24: 114 | U24: 174.42 | V24: 0 | W24: N | X24: =IF(Table2[[#This Row],[Qty available]]>Table2[[#This Row],[Qty on hand]],"Check","OK") -> OK
A25: IT-10001 | B25: Ball bearing 20-1 | C25: Bearings | D25: Clearwater Supply | E25: Main warehouse | F25: 2026-08 | G25: 1.13 | H25: 1.13 | I25: 1.12625 | J25: 1.53 | K25: 25 | L25: 40 | M25: 192 | N25: 280 | O25: 315.35 | P25: 57 | Q25: 223 | R25: 6.57 | S25: 2 | T25: 276 | U25: 422.28 | V25: 0 | W25: N | X25: =IF(Table2[[#This Row],[Qty available]]>Table2[[#This Row],[Qty on hand]],"Check","OK") -> OK
A26: IT-10002 | B26: Ball bearing A-2 | C26: Bearings | D26: Clearwater Supply | E26: Main warehouse | F26: 2024-09 | G26: 3.74 | H26: 4.05 | I26: 3.94 | J26: 5.58 | K26: 59 | M26: 0 | N26: 0 | O26: 0 | P26: 0 | Q26: 0 | S26: 230 | T26: 0 | U26: 0 | V26: 0 | W26: N | X26: =IF(Table2[[#This Row],[Qty available]]>Table2[[#This Row],[Qty on hand]],"Check","OK") -> OK
A27: IT-10002 | B27: Ball bearing A-2 | C27: Bearings | D27: Clearwater Supply | E27: Main warehouse | F27: 2024-10 | G27: 3.81 | H27: 4.12 | I27: 3.94 | J27: 5.58 | K27: 59 | M27: 0 | N27: 0 | O27: 0 | P27: 0 | Q27: 0 | S27: 261 | T27: 0 | U27: 0 | V27: 0 | W27: N | X27: =IF(Table2[[#This Row],[Qty available]]>Table2[[#This Row],[Qty on hand]],"Check","OK") -> OK
A28: IT-10002 | B28: Ball bearing A-2 | C28: Bearings | D28: Clearwater Supply | E28: Main warehouse | F28: 2024-11 | G28: 3.76 | H28: 4.07 | I28: 3.94 | J28: 5.58 | K28: 59 | M28: 0 | N28: 0 | O28: 0 | P28: 0 | Q28: 0 | S28: 291 | T28: 0 | U28: 0 | V28: 0 | W28: N | X28: =IF(Table2[[#This Row],[Qty available]]>Table2[[#This Row],[Qty on hand]],"Check","OK") -> OK
A29: IT-10002 | B29: Ball bearing A-2 | C29: Bearings | D29: Clearwater Supply | E29: Main warehouse | F29: 2024-12 | G29: 3.75 | H29: 4.06 | I29: 3.94 | J29: 5.58 | K29: 59 | M29: 0 | N29: 0 | O29: 0 | P29: 0 | Q29: 0 | S29: 322 | T29: 0 | U29: 0 | V29: 0 | W29: N | X29: =IF(Table2[[#This Row],[Qty available]]>Table2[[#This Row],[Qty on hand]],"Check","OK") -> OK
A30: IT-10002 | B30: Ball bearing A-2 | C30: Bearings | D30: Clearwater Supply | E30: Main warehouse | F30: 2025-01 | G30: 3.82 | H30: 4.13 | I30: 3.94 | J30: 5.58 | K30: 59 | M30: 0 | N30: 0 | O30: 0 | P30: 0 | Q30: 0 | S30: 353 | T30: 0 | U30: 0 | V30: 0 | W30: N | X30: =IF(Table2[[#This Row],[Qty available]]>Table2[[#This Row],[Qty on hand]],"Check","OK") -> OK
A31: IT-10002 | B31: Ball bearing A-2 | C31: Bearings | D31: Clearwater Supply | E31: Main warehouse | F31: 2025-02 | G31: 3.74 | H31: 4.05 | I31: 3.94 | J31: 5.74 | K31: 59 | M31: 0 | N31: 0 | O31: 0 | P31: 0 | Q31: 0 | S31: 381 | T31: 0 | U31: 0 | V31: 0 | W31: N | X31: =IF(Table2[[#This Row],[Qty available]]>Table2[[#This Row],[Qty on hand]],"Check","OK") -> OK
A32: IT-10002 | B32: Ball bearing A-2 | C32: Bearings | D32: Clearwater Supply | E32: Main warehouse | F32: 2025-03 | G32: 3.68 | H32: 3.98 | I32: 3.98 | J32: 5.74 | K32: 59 | L32: 53 | M32: 56 | N32: 56 | O32: 222.88 | P32: 0 | Q32: 56 | S32: 412 | T32: 0 | U32: 0 | V32: 0 | W32: N | X32: =IF(Table2[[#This Row],[Qty available]]>Table2[[#This Row],[Qty on hand]],"Check","OK") -> OK
A33: IT-10002 | B33: Ball bearing A-2 | C33: Bearings | D33: Clearwater Supply | E33: Main warehouse | F33: 2025-04 | G33: 3.89 | H33: 4.21 | I33: 4.140378 | J33: 5.74 | K33: 59 | L33: 51 | M33: 129 | N33: 185 | O33: 765.97 | P33: 0 | Q33: 185 | S33: 442 | T33: 0 | U33: 0 | V33: 0 | W33: N | X33: =IF(Table2[[#This Row],[Qty available]]>Table2[[#This Row],[Qty on hand]],"Check","OK") -> OK
A34: IT-10002 | B34: Ball bearing A-2 | C34: Bearings | D34: Clearwater Supply | E34: Main warehouse | F34: 2025-05 | G34: 3.79 | H34: 4.1 | I34: 4.110071 | J34: 5.74 | K34: 59 | L34: 53 | M34: 557 | N34: 567 | O34: 2330.41 | P34: 31 | Q34: 536 | R34: 42.58 | S34: 1 | T34: 175 | U34: 1004.5 | V34: 0 | W34: N | X34: =IF(Table2[[#This Row],[Qty available]]>Table2[[#This Row],[Qty on hand]],"Check","OK") -> OK
A35: IT-10002 | B35: Ball bearing A-2 | C35: Bearings | D35: Clearwater Supply | E35: Main warehouse | F35: 2025-06 | G35: 3.89 | H35: 4.21 | I35: 4.167138 | J35: 5.74 | K35: 59 | L35: 57 | M35: 755 | N35: 1153 | O35: 4804.71 | P35: 27 | Q35: 1126 | R35: 43.57 | S35: 8 | T35: 169 | U35: 970.06 | V35: 0 | W35: N | X35: =IF(Table2[[#This Row],[Qty available]]>Table2[[#This Row],[Qty on hand]],"Check","OK") -> OK
A36: IT-10002 | B36: Ball bearing A-2 | C36: Bearings | D36: Clearwater Supply | E36: Main warehouse | F36: 2025-07 | G36: 3.79 | H36: 4.1 | I36: 4.148627 | J36: 5.74 | K36: 59 | L36: 59 | M36: 439 | N36: 1209 | O36: 5015.69 | P36: 94 | Q36: 1115 | R36: 21.86 | S36: 2 | T36: 383 | U36: 2198.42 | V36: 0 | W36: N | X36: =IF(Table2[[#This Row],[Qty available]]>Table2[[#This Row],[Qty on hand]],"Check","OK") -> OK
A37: IT-10002 | B37: Ball bearing A-2 | C37: Bearings | D37: Clearwater Supply | E37: Main warehouse | F37: 2025-08 | G37: 3.87 | H37: 4.19 | I37: 4.161434 | J37: 5.74 | K37: 59 | L37: 59 | M37: 542 | N37: 1283 | O37: 5339.12 | P37: 67 | Q37: 1216 | R37: 16.53 | S37: 0 | T37: 468 | U37: 2686.32 | V37: 0 | W37: N | X37: =IF(Table2[[#This Row],[Qty available]]>Table2[[#This Row],[Qty on hand]],"Check","OK") -> OK
A38: IT-10002 | B38: Ball bearing A-2 | C38: Bearings | D38: Clearwater Supply | E38: Main warehouse | F38: 2025-09 | G38: 3.79 | H38: 4.1 | I38: 4.15027 | J38: 5.74 | K38: 59 | L38: 53 | M38: 285 | N38: 1445 | O38: 5997.14 | P38: 40 | Q38: 1405 | R38: 19.5 | S38: 4 | T38: 123 | U38: 706.02 | V38: 0 | W38: N | X38: =IF(Table2[[#This Row],[Qty available]]>Table2[[#This Row],[Qty on hand]],"Check","OK") -> OK
A39: IT-10002 | B39: Ball bearing A-2 | C39: Bearings | D39: Clearwater Supply | E39: Main warehouse | F39: 2025-10 | G39: 3.91 | H39: 4.23 | I39: 4.15027 | J39: 5.74 | K39: 59 | M39: 0 | N39: 999 | O39: 4146.12 | P39: 54 | Q39: 945 | R39: 12.66 | S39: 1 | T39: 446 | U39: 2560.04 | V39: 0 | W39: N | X39: =IF(Table2[[#This Row],[Qty available]]>Table2[[#This Row],[Qty on hand]],"Check","OK") -> OK
A40: IT-10002 | B40: Ball bearing A-2 | C40: Bearings | D40: Clearwater Supply | E40: Main warehouse | F40: 2025-11 | G40: 3.84 | H40: 4.16 | I40: 4.15027 | J40: 5.74 | K40: 59 | M40: 0 | N40: 666 | O40: 2764.08 | P40: 121 | Q40: 545 | R40: 9.6 | S40: 0 | T40: 333 | U40: 1911.42 | V40: 0 | W40: N | X40: =IF(Table2[[#This Row],[Qty available]]>Table2[[#This Row],[Qty on hand]],"Check","OK") -> OK
A41: IT-10002 | B41: Ball bearing A-2 | C41: Bearings | D41: Clearwater Supply | E41: Main warehouse | F41: 2025-12 | G41: 3.87 | H41: 4.19 | I41: 4.174873 | J41: 5.74 | K41: 59 | L41: 52 | M41: 1083 | N41: 1461 | O41: 6099.49 | P41: 94 | Q41: 1367 | R41: 18 | S41: 4 | T41: 288 | U41: 1653.12 | V41: 0 | W41: N | X41: =IF(Table2[[#This Row],[Qty available]]>Table2[[#This Row],[Qty on hand]],"Check","OK") -> OK
A42: IT-10002 | B42: Ball bearing A-2 | C42: Bearings | D42: Clearwater Supply | E42: Main warehouse | F42: 2026-01 | G42: 3.88 | H42: 4.2 | I42: 4.174869 | J42: 5.74 | K42: 59 | M42: 0 | N42: 1029 | O42: 4295.94 | P42: 27 | Q42: 1002 | R42: 12.84 | S42: 0 | T42: 432 | U42: 2479.68 | V42: 0 | W42: N | X42: =IF(Table2[[#This Row],[Qty available]]>Table2[[#This Row],[Qty on hand]],"Check","OK") -> OK
A43: IT-10002 | B43: Ball bearing A-2 | C43: Bearings | D43: Clearwater Supply | E43: Main warehouse | F43: 2026-02 | G43: 3.9 | H43: 4.22 | I43: 4.174863 | J43: 5.91 | K43: 59 | M43: 0 | N43: 730 | O43: 3047.65 | P43: 40 | Q43: 690 | R43: 9.21 | S43: 0 | T43: 299 | U43: 1767.09 | V43: 0 | W43: N | X43: =IF(Table2[[#This Row],[Qty available]]>Table2[[#This Row],[Qty on hand]],"Check","OK") -> OK
A44: IT-10002 | B44: Ball bearing A-2 | C44: Bearings | D44: Clearwater Supply | E44: Main warehouse | F44: 2026-03 | G44: 3.82 | H44: 4.13 | I44: 4.174846 | J44: 5.91 | K44: 59 | M44: 0 | N44: 260 | O44: 1085.46 | P44: 67 | Q44: 193 | R44: 2.78 | S44: 0 | T44: 470 | U44: 2777.7 | V44: 0 | W44: N | X44: =IF(Table2[[#This Row],[Qty available]]>Table2[[#This Row],[Qty on hand]],"Check","OK") -> OK
A45: IT-10002 | B45: Ball bearing A-2 | C45: Bearings | D45: Clearwater Supply | E45: Main warehouse | F45: 2026-04 | G45: 3.94 | H45: 4.26 | I45: 4.238 | J45: 5.91 | K45: 59 | L45: 51 | M45: 746 | N45: 625 | O45: 2648.75 | P45: 54 | Q45: 571 | R45: 6.91 | S45: 1 | T45: 381 | U45: 2251.71 | V45: 0 | W45: N | X45: =IF(Table2[[#This Row],[Qty available]]>Table2[[#This Row],[Qty on hand]],"Check","OK") -> OK
A46: IT-10002 | B46: Ball bearing A-2 | C46: Bearings | D46: Clearwater Supply | E46: Main warehouse | F46: 2026-05 | G46: 4.02 | H46: 4.35 | I46: 4.302318 | J46: 5.91 | K46: 59 | L46: 106 | M46: 843 | N46: 811 | O46: 3489.18 | P46: 94 | Q46: 717 | R46: 7.07 | S46: 1 | T46: 657 | U46: 3882.87 | V46: 0 | W46: N | X46: =IF(Table2[[#This Row],[Qty available]]>Table2[[#This Row],[Qty on hand]],"Check","OK") -> OK
A47: IT-10002 | B47: Ball bearing A-2 | C47: Bearings | D47: Clearwater Supply | E47: Main warehouse | F47: 2026-06 | G47: 4.01 | H47: 4.34 | I47: 4.30728 | J47: 5.91 | K47: 59 | L47: 82 | M47: 123 | N47: 522 | O47: 2248.4 | P47: 80 | Q47: 442 | R47: 4.68 | S47: 0 | T47: 412 | U47: 2434.92 | V47: 0 | W47: N | X47: =IF(Table2[[#This Row],[Qty available]]>Table2[[#This Row],[Qty on hand]],"Check","OK") -> OK
A48: IT-10002 | B48: Ball bearing A-2 | C48: Bearings | D48: Clearwater Supply | E48: Main warehouse | F48: 2026-07 | G48: 4.04 | H48: 4.37 | I48: 4.347558 | J48: 5.91 | K48: 59 | L48: 53 | M48: 937 | N48: 782 | O48: 3399.79 | P48: 27 | Q48: 755 | R48: 5.89 | S48: 2 | T48: 677 | U48: 4001.07 | V48: 0 | W48: N | X48: =IF(Table2[[#This Row],[Qty available]]>Table2[[#This Row],[Qty on hand]],"Check","OK") -> OK
A49: IT-10002 | B49: Ball bearing A-2 | C49: Bearings | D49: Clearwater Supply | E49: Main warehouse | F49: 2026-08 | G49: 3.99 | H49: 4.32 | I49: 4.347565 | J49: 5.91 | K49: 59 | M49: 0 | N49: 271 | O49: 1178.19 | P49: 40 | Q49: 231 | R49: 2.23 | S49: 5 | T49: 511 | U49: 3020.01 | V49: 0 | W49: N | X49: =IF(Table2[[#This Row],[Qty available]]>Table2[[#This Row],[Qty on hand]],"Check","OK") -> OK
A50: IT-10003 | B50: Pressure valve A-3 | C50: Fluid power | D50: Summit Trading | E50: Main warehouse | F50: 2024-09 | G50: 73.42 | H50: 79.16 | I50: 79.082593 | J50: 109.31 | K50: 31 | M50: 0 | N50: 27 | O50: 2135.23 | P50: 13 | Q50: 14 | R50: 2.43 | S50: 4 | T50: 48 | U50: 5246.88 | V50: 0 | W50: N | X50: =IF(Table2[[#This Row],[Qty available]]>Table2[[#This Row],[Qty on hand]],"Check","OK") -> OK
A51: IT-10003 | B51: Pressure valve A-3 | C51: Fluid power | D51: Summit Trading | E51: Main warehouse | F51: 2024-10 | G51: 72.04 | H51: 77.67 | I51: 78.22 | J51: 109.31 | K51: 31 | L51: 46 | M51: 42 | N51: 1 | O51: 78.22 | P51: 1 | Q51: 0 | R51: 0.07 | S51: 1 | T51: 68 | U51: 7433.08 | V51: 0 | W51: N | X51: =IF(Table2[[#This Row],[Qty available]]>Table2[[#This Row],[Qty on hand]],"Check","OK") -> OK
A52: IT-10003 | B52: Pressure valve A-3 | C52: Fluid power | D52: Summit Trading | E52: Main warehouse | F52: 2024-11 | G52: 72.44 | H52: 78.1 | I52: 78.100846 | J52: 109.31 | K52: 31 | L52: 29 | M52: 143 | N52: 130 | O52: 10153.11 | P52: 8 | Q52: 122 | R52: 13 | S52: 3 | T52: 14 | U52: 1530.34 | V52: 0 | W52: N | X52: =IF(Table2[[#This Row],[Qty available]]>Table2[[#This Row],[Qty on hand]],"Check","OK") -> OK
A53: IT-10003 | B53: Pressure valve A-3 | C53: Fluid power | D53: Summit Trading | E53: Main warehouse | F53: 2024-12 | G53: 73.39 | H53: 79.13 | I53: 78.1008 | J53: 109.31 | K53: 31 | M53: 0 | N53: 100 | O53: 7810.08 | P53: 14 | Q53: 86 | R53: 11.73 | S53: 3 | T53: 30 | U53: 3279.3 | V53: 0 | W53: N | X53: =IF(Table2[[#This Row],[Qty available]]>Table2[[#This Row],[Qty on hand]],"Check","OK") -> OK
A54: IT-10003 | B54: Pressure valve A-3 | C54: Fluid power | D54: Summit Trading | E54: Main warehouse | F54: 2025-01 | G54: 75.67 | H54: 81.59 | I54: 79.132783 | J54: 109.31 | K54: 31 | L54: 28 | M54: 42 | N54: 115 | O54: 9100.27 | P54: 10 | Q54: 105 | R54: 21.29 | S54: 8 | T54: 27 | U54: 2951.37 | V54: 0 | W54: N | X54: =IF(Table2[[#This Row],[Qty available]]>Table2[[#This Row],[Qty on hand]],"Check","OK") -> OK
A55: IT-10003 | B55: Pressure valve A-3 | C55: Fluid power | D55: Summit Trading | E55: Main warehouse | F55: 2025-02 | G55: 75.65 | H55: 81.56 | I55: 79.132796 | J55: 115.5 | K55: 31 | M55: 0 | N55: 93 | O55: 7359.35 | P55: 10 | Q55: 83 | R55: 15.14 | S55: 15 | T55: 22 | U55: 2541 | V55: 0 | W55: N | X55: =IF(Table2[[#This Row],[Qty available]]>Table2[[#This Row],[Qty on hand]],"Check","OK") -> OK
A56: IT-10003 | B56: Pressure valve A-3 | C56: Fluid power | D56: Summit Trading | E56: Main warehouse | F56: 2025-03 | G56: 73.96 | H56: 79.74 | I56: 79.321647 | J56: 115.5 | K56: 31 | L56: 28 | M56: 42 | N56: 85 | O56: 6742.34 | P56: 13 | Q56: 72 | R56: 11.04 | S56: 2 | T56: 50 | U56: 5775 | V56: 0 | W56: N | X56: =IF(Table2[[#This Row],[Qty available]]>Table2[[#This Row],[Qty on hand]],"Check","OK") -> OK
A57: IT-10003 | B57: Pressure valve A-3 | C57: Fluid power | D57: Summit Trading | E57: Main warehouse | F57: 2025-04 | G57: 76.64 | H57: 82.63 | I57: 79.321667 | J57: 115.5 | K57: 31 | M57: 0 | N57: 72 | O57: 5711.16 | P57: 14 | Q57: 58 | R57: 10.77 | S57: 6 | T57: 13 | U57: 1501.5 | V57: 0 | W57: N | X57: =IF(Table2[[#This Row],[Qty available]]>Table2[[#This Row],[Qty on hand]],"Check","OK") -> OK
A58: IT-10003 | B58: Pressure valve A-3 | C58: Fluid power | D58: Summit Trading | E58: Main warehouse | F58: 2025-05 | G58: 74.17 | H58: 79.97 | I58: 79.32 | J58: 115.5 | K58: 31 | M58: 0 | N58: 2 | O58: 158.64 | P58: 2 | Q58: 0 | R58: 0.2 | S58: 3 | T58: 70 | U58: 8085 | V58: 0 | W58: N | X58: =IF(Table2[[#This Row],[Qty available]]>Table2[[#This Row],[Qty on hand]],"Check","OK") -> OK
A59: IT-10003 | B59: Pressure valve A-3 | C59: Fluid power | D59: Summit Trading | E59: Main warehouse | F59: 2025-06 | G59: 74.21 | H59: 80.01 | I59: 80.000777 | J59: 115.5 | K59: 31 | L59: 30 | M59: 148 | N59: 103 | O59: 8240.08 | P59: 4 | Q59: 99 | R59: 10.3 | S59: 3 | T59: 47 | U59: 5428.5 | V59: 0 | W59: N | X59: =IF(Table2[[#This Row],[Qty available]]>Table2[[#This Row],[Qty on hand]],"Check","OK") -> OK
A60: IT-10003 | B60: Pressure valve A-3 | C60: Fluid power | D60: Summit Trading | E60: Main warehouse | F60: 2025-07 | G60: 76.39 | H60: 82.36 | I60: 80.938908 | J60: 115.5 | K60: 31 | L60: 30 | M60: 68 | N60: 119 | O60: 9631.73 | P60: 3 | Q60: 116 | R60: 9.25 | S60: 5 | T60: 52 | U60: 6006 | V60: 0 | W60: N | X60: =IF(Table2[[#This Row],[Qty available]]>Table2[[#This Row],[Qty on hand]],"Check","OK") -> OK
A61: IT-10003 | B61: Pressure valve A-3 | C61: Fluid power | D61: Summit Trading | E61: Main warehouse | F61: 2025-08 | G61: 75.51 | H61: 81.41 | I61: 80.938833 | J61: 115.5 | K61: 31 | M61: 0 | N61: 60 | O61: 4856.33 | P61: 4 | Q61: 56 | R61: 4.99 | S61: 0 | T61: 59 | U61: 6814.5 | V61: 0 | W61: N | X61: =IF(Table2[[#This Row],[Qty available]]>Table2[[#This Row],[Qty on hand]],"Check","OK") -> OK
A62: IT-10003 | B62: Pressure valve A-3 | C62: Fluid power | D62: Summit Trading | E62: Main warehouse | F62: 2025-09 | G62: 76.18 | H62: 82.14 | I62: 81.513289 | J62: 115.5 | K62: 31 | L62: 29 | M62: 55 | N62: 76 | O62: 6195.01 | P62: 6 | Q62: 70 | R62: 6.66 | S62: 8 | T62: 39 | U62: 4504.5 | V62: 0 | W62: N | X62: =IF(Table2[[#This Row],[Qty available]]>Table2[[#This Row],[Qty on hand]],"Check","OK") -> OK
A63: IT-10003 | B63: Pressure valve A-3 | C63: Fluid power | D63: Summit Trading | E63: Main warehouse | F63: 2025-10 | G63: 75.44 | H63: 81.34 | I63: 81.433467 | J63: 115.5 | K63: 31 | L63: 29 | M63: 65 | N63: 75 | O63: 6107.51 | P63: 8 | Q63: 67 | R63: 6.01 | S63: 2 | T63: 66 | U63: 7623 | V63: 0 | W63: N | X63: =IF(Table2[[#This Row],[Qty available]]>Table2[[#This Row],[Qty on hand]],"Check","OK") -> OK
A64: IT-10003 | B64: Pressure valve A-3 | C64: Fluid power | D64: Summit Trading | E64: Main warehouse | F64: 2025-11 | G64: 75.41 | H64: 81.31 | I64: 81.381724 | J64: 115.5 | K64: 31 | L64: 28 | M64: 54 | N64: 58 | O64: 4720.14 | P64: 6 | Q64: 52 | R64: 4.28 | S64: 1 | T64: 71 | U64: 8200.5 | V64: 0 | W64: N | X64: =IF(Table2[[#This Row],[Qty available]]>Table2[[#This Row],[Qty on hand]],"Check","OK") -> OK
A65: IT-10003 | B65: Pressure valve A-3 | C65: Fluid power | D65: Summit Trading | E65: Main warehouse | F65: 2025-12 | G65: 74.6 | H65: 80.43 | I65: 81.381724 | J65: 115.5 | K65: 31 | M65: 0 | N65: 0 | O65: 0 | P65: 0 | Q65: 0 | R65: 0 | S65: 0 | T65: 58 | U65: 6699 | V65: 10 | W65: Y | X65: =IF(Table2[[#This Row],[Qty available]]>Table2[[#This Row],[Qty on hand]],"Check","OK") -> OK
A66: IT-10003 | B66: Pressure valve A-3 | C66: Fluid power | D66: Summit Trading | E66: Main warehouse | F66: 2026-01 | G66: 76.72 | H66: 82.72 | I66: 82.72 | J66: 115.5 | K66: 31 | L66: 31 | M66: 151 | N66: 99 | O66: 8189.28 | P66: 7 | Q66: 92 | R66: 7.19 | S66: 11 | T66: 52 | U66: 6006 | V66: 0 | W66: N | X66: =IF(Table2[[#This Row],[Qty available]]>Table2[[#This Row],[Qty on hand]],"Check","OK") -> OK
A67: IT-10003 | B67: Pressure valve A-3 | C67: Fluid power | D67: Summit Trading | E67: Main warehouse | F67: 2026-02 | G67: 77.01 | H67: 83.03 | I67: 82.812353 | J67: 122.04 | K67: 31 | L67: 28 | M67: 42 | N67: 119 | O67: 9854.67 | P67: 4 | Q67: 115 | R67: 11.59 | S67: 0 | T67: 22 | U67: 2684.88 | V67: 0 | W67: N | X67: =IF(Table2[[#This Row],[Qty available]]>Table2[[#This Row],[Qty on hand]],"Check","OK") -> OK
A68: IT-10003 | B68: Pressure valve A-3 | C68: Fluid power | D68: Summit Trading | E68: Main warehouse | F68: 2026-03 | G68: 79.27 | H68: 85.47 | I68: 82.812308 | J68: 122.04 | K68: 31 | M68: 0 | N68: 78 | O68: 6459.36 | P68: 6 | Q68: 72 | R68: 8.72 | S68: 5 | T68: 41 | U68: 5003.64 | V68: 0 | W68: N | X68: =IF(Table2[[#This Row],[Qty available]]>Table2[[#This Row],[Qty on hand]],"Check","OK") -> OK
A69: IT-10003 | B69: Pressure valve A-3 | C69: Fluid power | D69: Summit Trading | E69: Main warehouse | F69: 2026-04 | G69: 76.84 | H69: 82.85 | I69: 82.826145 | J69: 122.04 | K69: 31 | L69: 27 | M69: 45 | N69: 83 | O69: 6874.57 | P69: 4 | Q69: 79 | R69: 10.25 | S69: 8 | T69: 40 | U69: 4881.6 | V69: 0 | W69: N | X69: =IF(Table2[[#This Row],[Qty available]]>Table2[[#This Row],[Qty on hand]],"Check","OK") -> OK
A70: IT-10003 | B70: Pressure valve A-3 | C70: Fluid power | D70: Summit Trading | E70: Main warehouse | F70: 2026-05 | G70: 78.21 | H70: 84.33 | I70: 82.826053 | J70: 122.04 | K70: 31 | M70: 0 | N70: 38 | O70: 3147.39 | P70: 13 | Q70: 25 | R70: 3.96 | S70: 2 | T70: 45 | U70: 5491.8 | V70: 0 | W70: N | X70: =IF(Table2[[#This Row],[Qty available]]>Table2[[#This Row],[Qty on hand]],"Check","OK") -> OK
A71: IT-10003 | B71: Pressure valve A-3 | C71: Fluid power | D71: Summit Trading | E71: Main warehouse | F71: 2026-06 | G71: 78.26 | H71: 84.38 | I71: 83.650909 | J71: 122.04 | K71: 31 | L71: 27 | M71: 43 | N71: 22 | O71: 1840.32 | P71: 11 | Q71: 11 | R71: 1.99 | S71: 2 | T71: 59 | U71: 7200.36 | V71: 0 | W71: N | X71: =IF(Table2[[#This Row],[Qty available]]>Table2[[#This Row],[Qty on hand]],"Check","OK") -> OK
A72: IT-10003 | B72: Pressure valve A-3 | C72: Fluid power | D72: Summit Trading | E72: Main warehouse | F72: 2026-07 | G72: 77.62 | H72: 83.69 | I72: 83.650909 | J72: 122.04 | K72: 31 | M72: 0 | N72: 0 | O72: 0 | P72: 0 | Q72: 0 | R72: 0 | S72: 1 | T72: 22 | U72: 2684.88 | V72: 53 | W72: Y | X72: =IF(Table2[[#This Row],[Qty available]]>Table2[[#This Row],[Qty on hand]],"Check","OK") -> OK
A73: IT-10003 | B73: Pressure valve A-3 | C73: Fluid power | D73: Summit Trading | E73: Main warehouse | F73: 2026-08 | G73: 78.16 | H73: 84.27 | I73: 84.27 | J73: 122.04 | K73: 31 | L73: 44 | M73: 48 | N73: 0 | O73: 0 | P73: 0 | Q73: 0 | R73: 0 | S73: 8 | T73: 48 | U73: 5857.92 | V73: 4 | W73: Y | X73: =IF(Table2[[#This Row],[Qty available]]>Table2[[#This Row],[Qty on hand]],"Check","OK") -> OK
A74: IT-10004 | B74: Filter cartridge A-4 | C74: Fluid power | D74: Summit Trading | E74: Main warehouse | F74: 2024-09 | G74: 90.37 | H74: 90.37 | I74: 89.853333 | J74: 123.98 | K74: 39 | M74: 0 | N74: 0 | O74: 0 | P74: 0 | Q74: 0 | R74: 0 | S74: 15 | T74: 21 | U74: 2603.58 | V74: 1 | W74: Y | X74: =IF(Table2[[#This Row],[Qty available]]>Table2[[#This Row],[Qty on hand]],"Check","OK") -> OK
A75: IT-10004 | B75: Filter cartridge A-4 | C75: Fluid power | D75: Summit Trading | E75: Main warehouse | F75: 2024-10 | G75: 89.14 | H75: 89.14 | I75: 89.14 | J75: 123.98 | K75: 39 | L75: 37 | M75: 33 | N75: 22 | O75: 1961.08 | P75: 5 | Q75: 17 | R75: 6.43 | S75: 0 | T75: 11 | U75: 1363.78 | V75: 0 | W75: N | X75: =IF(Table2[[#This Row],[Qty available]]>Table2[[#This Row],[Qty on hand]],"Check","OK") -> OK
A76: IT-10004 | B76: Filter cartridge A-4 | C76: Fluid power | D76: Summit Trading | E76: Main warehouse | F76: 2024-11 | G76: 88.63 | H76: 88.63 | I76: 88.933125 | J76: 123.98 | K76: 39 | L76: 36 | M76: 15 | N76: 16 | O76: 1422.93 | P76: 2 | Q76: 14 | R76: 3.92 | S76: 7 | T76: 21 | U76: 2603.58 | V76: 0 | W76: N | X76: =IF(Table2[[#This Row],[Qty available]]>Table2[[#This Row],[Qty on hand]],"Check","OK") -> OK
A77: IT-10004 | B77: Filter cartridge A-4 | C77: Fluid power | D77: Summit Trading | E77: Main warehouse | F77: 2024-12 | G77: 89.59 | H77: 89.59 | I77: 89.271333 | J77: 123.98 | K77: 39 | L77: 37 | M77: 17 | N77: 15 | O77: 1339.07 | P77: 1 | Q77: 14 | R77: 3.94 | S77: 0 | T77: 18 | U77: 2231.64 | V77: 0 | W77: N | X77: =IF(Table2[[#This Row],[Qty available]]>Table2[[#This Row],[Qty on hand]],"Check","OK") -> OK
A78: IT-10004 | B78: Filter cartridge A-4 | C78: Fluid power | D78: Summit Trading | E78: Main warehouse | F78: 2025-01 | G78: 94.02 | H78: 94.02 | I78: 91.722105 | J78: 123.98 | K78: 39 | L78: 38 | M78: 16 | N78: 19 | O78: 1742.72 | P78: 4 | Q78: 15 | R78: 4.9 | S78: 0 | T78: 12 | U78: 1487.76 | V78: 0 | W78: N | X78: =IF(Table2[[#This Row],[Qty available]]>Table2[[#This Row],[Qty on hand]],"Check","OK") -> OK
A79: IT-10004 | B79: Filter cartridge A-4 | C79: Fluid power | D79: Summit Trading | E79: Main warehouse | F79: 2025-02 | G79: 93.27 | H79: 93.27 | I79: 92.404815 | J79: 129.43 | K79: 39 | L79: 38 | M79: 15 | N79: 27 | O79: 2494.93 | P79: 3 | Q79: 24 | R79: 9.38 | S79: 1 | T79: 7 | U79: 906.01 | V79: 0 | W79: N | X79: =IF(Table2[[#This Row],[Qty available]]>Table2[[#This Row],[Qty on hand]],"Check","OK") -> OK
A80: IT-10004 | B80: Filter cartridge A-4 | C80: Fluid power | D80: Summit Trading | E80: Main warehouse | F80: 2025-03 | G80: 94.51 | H80: 94.51 | I80: 92.404545 | J80: 129.43 | K80: 39 | M80: 0 | N80: 11 | O80: 1016.45 | P80: 2 | Q80: 9 | R80: 4.04 | S80: 3 | T80: 16 | U80: 2070.88 | V80: 0 | W80: N | X80: =IF(Table2[[#This Row],[Qty available]]>Table2[[#This Row],[Qty on hand]],"Check","OK") -> OK
A81: IT-10004 | B81: Filter cartridge A-4 | C81: Fluid power | D81: Summit Trading | E81: Main warehouse | F81: 2025-04 | G81: 93.05 | H81: 93.05 | I81: 92.404545 | J81: 129.43 | K81: 39 | M81: 0 | N81: 0 | O81: 0 | P81: 0 | Q81: 0 | R81: 0 | S81: 3 | T81: 11 | U81: 1423.73 | V81: 14 | W81: Y | X81: =IF(Table2[[#This Row],[Qty available]]>Table2[[#This Row],[Qty on hand]],"Check","OK") -> OK
A82: IT-10004 | B82: Filter cartridge A-4 | C82: Fluid power | D82: Summit Trading | E82: Main warehouse | F82: 2025-05 | G82: 94.58 | H82: 94.58 | I82: 94.58 | J82: 129.43 | K82: 39 | L82: 34 | M82: 46 | N82: 39 | O82: 3688.62 | P82: 4 | Q82: 35 | R82: 15.08 | S82: 9 | T82: 7 | U82: 906.01 | V82: 0 | W82: N | X82: =IF(Table2[[#This Row],[Qty available]]>Table2[[#This Row],[Qty on hand]],"Check","OK") -> OK
A83: IT-10004 | B83: Filter cartridge A-4 | C83: Fluid power | D83: Summit Trading | E83: Main warehouse | F83: 2025-06 | G83: 94.06 | H83: 94.06 | I83: 94.58 | J83: 129.43 | K83: 39 | M83: 0 | N83: 29 | O83: 2742.82 | P83: 4 | Q83: 25 | R83: 13.46 | S83: 9 | T83: 10 | U83: 1294.3 | V83: 0 | W83: N | X83: =IF(Table2[[#This Row],[Qty available]]>Table2[[#This Row],[Qty on hand]],"Check","OK") -> OK
A84: IT-10004 | B84: Filter cartridge A-4 | C84: Fluid power | D84: Summit Trading | E84: Main warehouse | F84: 2025-07 | G84: 92.48 | H84: 92.48 | I84: 93.864074 | J84: 129.43 | K84: 39 | L84: 37 | M84: 15 | N84: 27 | O84: 2534.33 | P84: 3 | Q84: 24 | R84: 10.44 | S84: 3 | T84: 17 | U84: 2200.31 | V84: 0 | W84: N | X84: =IF(Table2[[#This Row],[Qty available]]>Table2[[#This Row],[Qty on hand]],"Check","OK") -> OK
A85: IT-10004 | B85: Filter cartridge A-4 | C85: Fluid power | D85: Summit Trading | E85: Main warehouse | F85: 2025-08 | G85: 91.79 | H85: 91.79 | I85: 93.123333 | J85: 129.43 | K85: 39 | L85: 37 | M85: 15 | N85: 24 | O85: 2234.96 | P85: 4 | Q85: 20 | R85: 7.01 | S85: 6 | T85: 18 | U85: 2329.74 | V85: 0 | W85: N | X85: =IF(Table2[[#This Row],[Qty available]]>Table2[[#This Row],[Qty on hand]],"Check","OK") -> OK
A86: IT-10004 | B86: Filter cartridge A-4 | C86: Fluid power | D86: Summit Trading | E86: Main warehouse | F86: 2025-09 | G86: 92.99 | H86: 92.99 | I86: 93.123529 | J86: 129.43 | K86: 39 | M86: 0 | N86: 17 | O86: 1583.1 | P86: 3 | Q86: 14 | R86: 5.32 | S86: 0 | T86: 7 | U86: 906.01 | V86: 0 | W86: N | X86: =IF(Table2[[#This Row],[Qty available]]>Table2[[#This Row],[Qty on hand]],"Check","OK") -> OK
A87: IT-10004 | B87: Filter cartridge A-4 | C87: Fluid power | D87: Summit Trading | E87: Main warehouse | F87: 2025-10 | G87: 91.28 | H87: 91.28 | I87: 92.259 | J87: 129.43 | K87: 39 | L87: 36 | M87: 15 | N87: 10 | O87: 922.59 | P87: 3 | Q87: 7 | R87: 2.8 | S87: 2 | T87: 22 | U87: 2847.46 | V87: 0 | W87: N | X87: =IF(Table2[[#This Row],[Qty available]]>Table2[[#This Row],[Qty on hand]],"Check","OK") -> OK
A88: IT-10004 | B88: Filter cartridge A-4 | C88: Fluid power | D88: Summit Trading | E88: Main warehouse | F88: 2025-11 | G88: 92.56 | H88: 92.56 | I88: 92.44 | J88: 129.43 | K88: 39 | L88: 54 | M88: 15 | N88: 12 | O88: 1109.28 | P88: 3 | Q88: 9 | R88: 3.71 | S88: 1 | T88: 13 | U88: 1682.59 | V88: 0 | W88: N | X88: =IF(Table2[[#This Row],[Qty available]]>Table2[[#This Row],[Qty on hand]],"Check","OK") -> OK
A89: IT-10004 | B89: Filter cartridge A-4 | C89: Fluid power | D89: Summit Trading | E89: Main warehouse | F89: 2025-12 | G89: 92.24 | H89: 92.24 | I89: 92.312857 | J89: 129.43 | K89: 39 | L89: 51 | M89: 21 | N89: 14 | O89: 1292.38 | P89: 4 | Q89: 10 | R89: 3.41 | S89: 4 | T89: 19 | U89: 2459.17 | V89: 0 | W89: N | X89: =IF(Table2[[#This Row],[Qty available]]>Table2[[#This Row],[Qty on hand]],"Check","OK") -> OK
A90: IT-10004 | B90: Filter cartridge A-4 | C90: Fluid power | D90: Summit Trading | E90: Main warehouse | F90: 2026-01 | G90: 97.29 | H90: 97.29 | I90: 94.887241 | J90: 129.43 | K90: 39 | L90: 36 | M90: 15 | N90: 29 | O90: 2751.73 | P90: 5 | Q90: 24 | R90: 11.91 | S90: 35 | T90: 0 | U90: 0 | V90: 0 | W90: N | X90: =IF(Table2[[#This Row],[Qty available]]>Table2[[#This Row],[Qty on hand]],"Check","OK") -> OK
A91: IT-10004 | B91: Filter cartridge A-4 | C91: Fluid power | D91: Summit Trading | E91: Main warehouse | F91: 2026-02 | G91: 98.19 | H91: 98.19 | I91: 96.013333 | J91: 135.12 | K91: 39 | L91: 36 | M91: 15 | N91: 24 | O91: 2304.32 | P91: 4 | Q91: 20 | R91: 7.91 | S91: 10 | T91: 20 | U91: 2702.4 | V91: 0 | W91: N | X91: =IF(Table2[[#This Row],[Qty available]]>Table2[[#This Row],[Qty on hand]],"Check","OK") -> OK
A92: IT-10004 | B92: Filter cartridge A-4 | C92: Fluid power | D92: Summit Trading | E92: Main warehouse | F92: 2026-03 | G92: 96.79 | H92: 96.79 | I92: 96.013077 | J92: 135.12 | K92: 39 | M92: 0 | N92: 13 | O92: 1248.17 | P92: 4 | Q92: 9 | R92: 5.39 | S92: 8 | T92: 11 | U92: 1486.32 | V92: 0 | W92: N | X92: =IF(Table2[[#This Row],[Qty available]]>Table2[[#This Row],[Qty on hand]],"Check","OK") -> OK
A93: IT-10004 | B93: Filter cartridge A-4 | C93: Fluid power | D93: Summit Trading | E93: Main warehouse | F93: 2026-04 | G93: 96.98 | H93: 96.98 | I93: 96.657857 | J93: 135.12 | K93: 39 | L93: 35 | M93: 26 | N93: 28 | O93: 2706.42 | P93: 3 | Q93: 25 | R93: 8.48 | S93: 0 | T93: 11 | U93: 1486.32 | V93: 0 | W93: N | X93: =IF(Table2[[#This Row],[Qty available]]>Table2[[#This Row],[Qty on hand]],"Check","OK") -> OK
A94: IT-10004 | B94: Filter cartridge A-4 | C94: Fluid power | D94: Summit Trading | E94: Main warehouse | F94: 2026-05 | G94: 96.87 | H94: 96.87 | I94: 96.732105 | J94: 135.12 | K94: 39 | L94: 38 | M94: 15 | N94: 19 | O94: 1837.91 | P94: 1 | Q94: 18 | R94: 5.43 | S94: 2 | T94: 24 | U94: 3242.88 | V94: 0 | W94: N | X94: =IF(Table2[[#This Row],[Qty available]]>Table2[[#This Row],[Qty on hand]],"Check","OK") -> OK
A95: IT-10004 | B95: Filter cartridge A-4 | C95: Fluid power | D95: Summit Trading | E95: Main warehouse | F95: 2026-06 | G95: 98.04 | H95: 98.04 | I95: 96.731667 | J95: 135.12 | K95: 39 | M95: 0 | N95: 6 | O95: 580.39 | P95: 5 | Q95: 1 | R95: 1.63 | S95: 0 | T95: 13 | U95: 1756.56 | V95: 0 | W95: N | X95: =IF(Table2[[#This Row],[Qty available]]>Table2[[#This Row],[Qty on hand]],"Check","OK") -> OK
A96: IT-10004 | B96: Filter cartridge A-4 | C96: Fluid power | D96: Summit Trading | E96: Main warehouse | F96: 2026-07 | G96: 98 | H96: 98 | I96: 97.695333 | J96: 135.12 | K96: 39 | L96: 38 | M96: 19 | N96: 15 | O96: 1465.43 | P96: 4 | Q96: 11 | R96: 4.19 | S96: 13 | T96: 10 | U96: 1351.2 | V96: 0 | W96: N | X96: =IF(Table2[[#This Row],[Qty available]]>Table2[[#This Row],[Qty on hand]],"Check","OK") -> OK
A97: IT-10004 | B97: Filter cartridge A-4 | C97: Fluid power | D97: Summit Trading | E97: Main warehouse | F97: 2026-08 | G97: 96.28 | H97: 96.28 | I97: 96.923 | J97: 135.12 | K97: 39 | L97: 35 | M97: 18 | N97: 10 | O97: 969.23 | P97: 1 | Q97: 9 | R97: 2.86 | S97: 2 | T97: 23 | U97: 3107.76 | V97: 0 | W97: N | X97: =IF(Table2[[#This Row],[Qty available]]>Table2[[#This Row],[Qty on hand]],"Check","OK") -> OK
A98: IT-10005 | B98: Hydraulic hose L-5 | C98: Fluid power | D98: Summit Trading | E98: Main warehouse | F98: 2024-09 | G98: 1.04 | H98: 1.11 | I98: 1.113124 | J98: 1.5 | K98: 16 | M98: 0 | N98: 477 | O98: 530.96 | P98: 62 | Q98: 415 | R98: 13.9 | S98: 0 | T98: 87 | U98: 130.5 | V98: 0 | W98: N | X98: =IF(Table2[[#This Row],[Qty available]]>Table2[[#This Row],[Qty on hand]],"Check","OK") -> OK
A99: IT-10005 | B99: Hydraulic hose L-5 | C99: Fluid power | D99: Summit Trading | E99: Main warehouse | F99: 2024-10 | G99: 1.03 | H99: 1.1 | I99: 1.108776 | J99: 1.5 | K99: 16 | L99: 21 | M99: 236 | N99: 441 | O99: 488.97 | P99: 62 | Q99: 379 | R99: 9.98 | S99: 2 | T99: 272 | U99: 408 | V99: 0 | W99: N | X99: =IF(Table2[[#This Row],[Qty available]]>Table2[[#This Row],[Qty on hand]],"Check","OK") -> OK
A100: IT-10005 | B100: Hydraulic hose L-5 | C100: Fluid power | D100: Summit Trading | E100: Main warehouse | F100: 2024-11 | G100: 1.04 | H100: 1.11 | I100: 1.109006 | J100: 1.5 | K100: 16 | L100: 21 | M100: 111 | N100: 312 | O100: 346.01 | P100: 23 | Q100: 289 | R100: 6.77 | S100: 0 | T100: 240 | U100: 360 | V100: 0 | W100: N | X100: =IF(Table2[[#This Row],[Qty available]]>Table2[[#This Row],[Qty on hand]],"Check","OK") -> OK
...

Sheet Stockout Status Distrirbution
A3: Row Labels | B3: Count of Stocked out (Y/N)
A4: N | B4: 3486
A5: Y | B5: 114
A6: Grand Total | B6: 3600

Sheet Revenue bu category
A3: Row Labels | B3: Sum of Revenue
A4: Bearings | B4: 5253716.7
A5: Electrical | B5: 4601753.6
A6: Fasteners | B6: 4548349.1
A7: Fluid power | B7: 6138005.6
A8: Power transmission | B8: 3224943.4
A9: Grand Total | B9: 23766768

Sheet Average Lead Time by Supplier
A3: Row Labels | B3: Average of Lead time actual days
A4: Clearwater Supply | B4: 37.14053
A5: Eastbrook Co | B5: 40.77027
A6: Granite Partners | B6: 38.564236
A7: Northfield Supply | B7: 33.553922
A8: Summit Trading | B8: 35.343173
A9: Grand Total | B9: 37.138155

Sheet Stock Value by Warehouse
A3: Row Labels | B3: Sum of Stock value
A4: Main warehouse | B4: 14262357
A5: North warehouse | B5: 23847966
A6: Grand Total | B6: 38110323

Sheet Lost Sales Units by Category
A3: Row Labels | B3: Sum of Lost sales units (stockout)
A4: Bearings | B4: 3501
A5: Electrical | B5: 3335
A6: Fasteners | B6: 4939
A7: Fluid power | B7: 2901
A8: Power transmission | B8: 1258
A9: Grand Total | B9: 15934

Sheet Sheet3
A3: Sum of Qty on hand | B3: Column Labels
A4: Row Labels | B4: Main warehouse | C4: North warehouse | D4: Grand Total
A5: Bearings | B5: 178259 | C5: 197933 | D5: 376192
A6: Electrical | B6: 190306 | C6: 327267 | D6: 517573
A7: Fasteners | B7: 88765 | C7: 252765 | D7: 341530
A8: Fluid power | B8: 147809 | C8: 187281 | D8: 335090
A9: Power transmission | B9: 43945 | C9: 218503 | D9: 262448
A10: Grand Total | B10: 649084 | C10: 1183749 | D10: 1832833
